MANIFEST.in
README.md
setup.py
sphinx_materialdesign_theme/__init__.py
sphinx_materialdesign_theme/drawer.html
sphinx_materialdesign_theme/footer.html
sphinx_materialdesign_theme/globaltoc.html
sphinx_materialdesign_theme/header.html
sphinx_materialdesign_theme/header_search.html
sphinx_materialdesign_theme/header_sourcelink.html
sphinx_materialdesign_theme/layout.html
sphinx_materialdesign_theme/localtoc.html
sphinx_materialdesign_theme/relations.html
sphinx_materialdesign_theme/search.html
sphinx_materialdesign_theme/theme.conf
sphinx_materialdesign_theme/__pycache__/__init__.cpython-36.pyc
sphinx_materialdesign_theme/static/material-icons.css
sphinx_materialdesign_theme/static/notosanscjkjp.css
sphinx_materialdesign_theme/static/roboto.css
sphinx_materialdesign_theme/static/sphinx_materialdesign_theme.css
sphinx_materialdesign_theme/static/sphinx_materialdesign_theme.js
sphinx_materialdesign_theme/static/font/NotoSansCJKjp/LICENSE_OFL.txt
sphinx_materialdesign_theme/static/font/NotoSansCJKjp/NotoSansCJKjp-Black.ttf
sphinx_materialdesign_theme/static/font/NotoSansCJKjp/NotoSansCJKjp-Black.woff
sphinx_materialdesign_theme/static/font/NotoSansCJKjp/NotoSansCJKjp-Black.woff2
sphinx_materialdesign_theme/static/font/NotoSansCJKjp/NotoSansCJKjp-Bold.ttf
sphinx_materialdesign_theme/static/font/NotoSansCJKjp/NotoSansCJKjp-Bold.woff
sphinx_materialdesign_theme/static/font/NotoSansCJKjp/NotoSansCJKjp-Bold.woff2
sphinx_materialdesign_theme/static/font/NotoSansCJKjp/NotoSansCJKjp-DemiLight.ttf
sphinx_materialdesign_theme/static/font/NotoSansCJKjp/NotoSansCJKjp-DemiLight.woff
sphinx_materialdesign_theme/static/font/NotoSansCJKjp/NotoSansCJKjp-DemiLight.woff2
sphinx_materialdesign_theme/static/font/NotoSansCJKjp/NotoSansCJKjp-Light.ttf
sphinx_materialdesign_theme/static/font/NotoSansCJKjp/NotoSansCJKjp-Light.woff
sphinx_materialdesign_theme/static/font/NotoSansCJKjp/NotoSansCJKjp-Light.woff2
sphinx_materialdesign_theme/static/font/NotoSansCJKjp/NotoSansCJKjp-Medium.ttf
sphinx_materialdesign_theme_nopyc.egg-info/PKG-INFO
sphinx_materialdesign_theme_nopyc.egg-info/SOURCES.txt
sphinx_materialdesign_theme_nopyc.egg-info/dependency_links.txt
sphinx_materialdesign_theme_nopyc.egg-info/entry_points.txt
sphinx_materialdesign_theme_nopyc.egg-info/top_level.txt